.bumbversion.cfg
.gitignore
MANIFEST.in
Makefile
README.md
requirements.txt
setup.py
shippable.yml
src/DecentLogs.egg-info/PKG-INFO
src/DecentLogs.egg-info/SOURCES.txt
src/DecentLogs.egg-info/dependency_links.txt
src/DecentLogs.egg-info/entry_points.txt
src/DecentLogs.egg-info/not-zip-safe
src/DecentLogs.egg-info/requires.txt
src/DecentLogs.egg-info/top_level.txt
src/decent_logs/__init__.py
src/decent_logs/log_record.py
src/decent_logs/withinternallog.py