Metadata-Version: 1.1
Name: DecentLogs
Version: 1.4.0
Summary:  Simple library to have objects keeping their log messages. 
Home-page: http://github.com/AndreaCensi/decent_logs
Author: Andrea Censi
Author-email: censi@mit.edu
License: UNKNOWN
Download-URL: http://github.com/AndreaCensi/decent_logs/tarball/1.4.0
Platform: UNKNOWN
Classifier: Development Status :: 4 - Beta
